<?xml version="1.0" encoding="UTF-8"?>
<!DOCTYPE suite SYSTEM "https://testng.org/testng-1.0.dtd">
<suite name="Suite" thread-count="2" parallel="tests">

<parameter name="Browser" value="Chromebrowser"></parameter>
  <test thread-count="5" name="Chrome">
    <classes>
      <class name="org.cross.Sample"/>
    </classes>
    </test>
    
    <parameter name="Browser" value="Firefoxbrowser"></parameter>
    <test thread-count="5" name="Firefox">
    <classes>
      <class name="org.cross.Sample"/>
    </classes>
    </test> <!-- Test -->
    
    
</suite> <!-- Suite -->
